src/__init__.py
src/examples/__init__.py
src/examples/cancel_order.py
src/examples/fill_order.py
src/examples/full_create_order.py
src/examples/full_fill_order.py
src/examples/get_nonce.py
src/examples/get_orders.py
src/examples/get_remaining_amount.py
src/examples/place_order.py
src/examples/sign_message.py
src/limit_order/__init__.py
src/limit_order/accounts.py
src/limit_order/constants.py
src/limit_order/limit_order.py
src/limit_order/mock_data.py
src/limit_order/personal_data.py
src/limit_order/sign_message.py
src/limit_order/types.py
src/limit_order/utils.py
src/return_types/__init__.py
src/return_types/orders.py
fibrous_limit_order_python_sdk-0.1.0.dist-info/LICENCE
fibrous_limit_order_python_sdk-0.1.0.dist-info/METADATA
fibrous_limit_order_python_sdk-0.1.0.dist-info/WHEEL
fibrous_limit_order_python_sdk-0.1.0.dist-info/top_level.txt
fibrous_limit_order_python_sdk-0.1.0.dist-info/RECORD
