Metadata-Version: 2.1
Name: fibrous-limit-order-python-sdk
Version: 0.1.0
Summary: A Python SDK for Fibrous Finance Limit Order
Home-page: https://github.com/Fibrous-Finance/limit-order-python-sdk
Author: zeroonesymphony
Author-email: kermo@fibrous.finance
Classifier: Programming Language :: Python :: 3
Classifier: License :: OSI Approved :: MIT License
Classifier: Operating System :: OS Independent
Requires-Python: >=3.6
License-File: LICENCE
